mpm/__init__.py
mpm/__main__.py
mpm/core/__init__.py
mpm/core/cli.py
mpm/core/configs.py
mpm/core/exceptions.py
mpm/core/logging.py
mpm/pm/__init__.py
mpm/pm/package_managers.py
mpm/pm/packages.py
mpm/scripts/__init__.py
mpm/scripts/bash.py
mpm/shell/__init__.py
mpm/shell/shells.py
mpm/utils/__init__.py
mpm/utils/json_parse.py
mpm/utils/string.py
mpm/utils/sys_info.py
mpm/utils/text_parse.py
mpm_core-0.1.3.data/data/configs/README.md
mpm_core-0.1.3.data/data/configs/known_packages.json
mpm_core-0.1.3.data/data/configs/settings.json
mpm_core-0.1.3.data/data/kits/README.md
mpm_core-0.1.3.data/data/scripts/clear_tmp_files.sh
mpm_core-0.1.3.data/data/scripts/colors_and_formatting_16.sh
mpm_core-0.1.3.data/data/scripts/header.sh
mpm_core-0.1.3.data/data/scripts/install_python3.sh
mpm_core-0.1.3.data/data/scripts/mylog.sh
mpm_core-0.1.3.data/data/scripts/tmp_test.sh
mpm_core-0.1.3.data/data/scripts/which_term.sh
mpm_core-0.1.3.dist-info/LICENSE
mpm_core-0.1.3.dist-info/METADATA
mpm_core-0.1.3.dist-info/WHEEL
mpm_core-0.1.3.dist-info/entry_points.txt
mpm_core-0.1.3.dist-info/top_level.txt
mpm_core-0.1.3.dist-info/RECORD
