Metadata-Version: 2.1
Name: mpm-core
Version: 0.1.3
Summary: 
Requires-Dist: click (>=7.0)
Requires-Dist: colorama
Requires-Dist: coloredlogs
Provides-Extra: test
Requires-Dist: pytest ; extra == 'test'
Requires-Dist: pytest-subprocess ; extra == 'test'
